comfy_reality/__init__.py
comfy_reality/exceptions.py
comfy_reality/py.typed
comfy_reality/nodes/__init__.py
comfy_reality/nodes/animation_builder.py
comfy_reality/nodes/ar_background_remover.py
comfy_reality/nodes/ar_optimizer.py
comfy_reality/nodes/base.py
comfy_reality/nodes/cross_platform_exporter.py
comfy_reality/nodes/flux_ar_generator.py
comfy_reality/nodes/material_composer.py
comfy_reality/nodes/physics_integrator.py
comfy_reality/nodes/reality_composer.py
comfy_reality/nodes/spatial_positioner.py
comfy_reality/nodes/usdz_exporter.py
comfy_reality/runtime/__init__.py
comfy_reality/runtime/cli.py
comfy_reality/runtime/core/__init__.py
comfy_reality/runtime/core/exceptions.py
comfy_reality/runtime/core/manager.py
comfy_reality/runtime/core/runtime.py
comfy_reality/runtime/ui/__init__.py
comfy_reality/runtime/ui/printer.py
comfy_reality/utils/__init__.py
comfy_reality/utils/image_utils.py
comfy_reality/utils/usdz_utils.py
comfy_reality/utils/uv_validation.py
comfy_reality/utils/validation.py
comfyui_reality-0.1.3.dist-info/METADATA
comfyui_reality-0.1.3.dist-info/WHEEL
comfyui_reality-0.1.3.dist-info/entry_points.txt
comfyui_reality-0.1.3.dist-info/RECORD
