Metadata-Version: 2.4
Name: comfyui-reality
Version: 0.1.3
Summary: Experimental AR/USDZ export toolkit for ComfyUI - Create AR-ready 3D content from existing workflows
Project-URL: Homepage, https://github.com/gerred/comfyui-reality
Project-URL: Repository, https://github.com/gerred/comfyui-reality
Project-URL: Issues, https://github.com/gerred/comfyui-reality/issues
Project-URL: Documentation, https://github.com/gerred/comfyui-reality#readme
Project-URL: Changelog, https://github.com/gerred/comfyui-reality/releases
Author-email: Gerred Dillon <hello@gerred.org>
Maintainer-email: Gerred Dillon <hello@gerred.org>
License: MIT
Keywords: 3d,ar,arkit,augmented-reality,comfyui,custom-nodes,ios,stickers,usdz
Classifier: Development Status :: 3 - Alpha
Classifier: Environment :: GPU :: NVIDIA CUDA
Classifier: Intended Audience :: Developers
Classifier: Intended Audience :: Education
Classifier: Intended Audience :: Science/Research
Classifier: License :: OSI Approved :: MIT License
Classifier: Operating System :: OS Independent
Classifier: Programming Language :: Python :: 3
Classifier: Programming Language :: Python :: 3.12
Classifier: Programming Language :: Python :: 3.13
Classifier: Topic :: Artistic Software
Classifier: Topic :: Multimedia :: Graphics :: 3D Modeling
Classifier: Topic :: Scientific/Engineering :: Artificial Intelligence
Classifier: Topic :: Software Development :: Libraries :: Python Modules
Requires-Python: >=3.12
Requires-Dist: click>=8.1.0
Requires-Dist: httpx>=0.25.0
Requires-Dist: numpy>=1.24.0
Requires-Dist: opencv-python>=4.8.0
Requires-Dist: pillow>=10.0.0
Requires-Dist: pydantic>=2.5.0
Requires-Dist: rich>=13.7.0
Requires-Dist: structlog>=23.2.0
Requires-Dist: torch>=2.0.0
Requires-Dist: torchvision>=0.15.0
Requires-Dist: trimesh>=4.0.0
Requires-Dist: websockets>=12.0
Provides-Extra: dev
Requires-Dist: anyio>=4.0.0; extra == 'dev'
Requires-Dist: build>=1.0.0; extra == 'dev'
Requires-Dist: comfy-cli>=1.4.1; extra == 'dev'
Requires-Dist: mypy>=1.5.0; extra == 'dev'
Requires-Dist: pre-commit>=3.4.0; extra == 'dev'
Requires-Dist: pytest-asyncio>=0.21.0; extra == 'dev'
Requires-Dist: pytest-cov>=4.1.0; extra == 'dev'
Requires-Dist: pytest-xdist>=3.3.0; extra == 'dev'
Requires-Dist: pytest>=7.4.0; extra == 'dev'
Requires-Dist: ruff>=0.1.0; extra == 'dev'
Requires-Dist: twine>=4.0.0; extra == 'dev'
Provides-Extra: docs
Requires-Dist: mkdocs-material>=9.2.0; extra == 'docs'
Requires-Dist: mkdocs>=1.5.0; extra == 'docs'
Requires-Dist: mkdocstrings[python]>=0.23.0; extra == 'docs'
Provides-Extra: full
Requires-Dist: usd-core>=23.11; extra == 'full'
Provides-Extra: usdz-export
Requires-Dist: usd-core>=23.11; extra == 'usdz-export'
